ngsdiffgeo/__init__.py
ngsdiffgeo/__init__.pyi
ngsdiffgeo/manifolds.py
ngsdiffgeo/manifolds.pyi
ngsdiffgeo/ngsdiffgeo.pyi
ngsdiffgeo/ngsdiffgeo.so
ngsdiffgeo/wrappers.py
ngsdiffgeo/wrappers.pyi
ngsdiffgeo-0.1.0.dist-info/METADATA
ngsdiffgeo-0.1.0.dist-info/WHEEL
ngsdiffgeo-0.1.0.dist-info/licenses/LICENSE
ngsdiffgeo-0.1.0.dist-info/RECORD
