Metadata-Version: 2.2
Name: ngsdiffgeo
Version: 0.1.0
Summary: Differential geometry tools for NGSolve
Author: Michael Neunteufel
Classifier: License :: OSI Approved :: GNU Lesser General Public License v3 (LGPLv3)
Project-URL: github, https://github.com/MichaelNeunteufel/NGSDiffGeo
Requires-Python: >=3.9
Requires-Dist: ngsolve==6.2.2506.post199.dev0
